freedom_search/__init__.py
freedom_search/enhancer.py
freedom_search/utils.py
freedom_search/search_engines/__init__.py
freedom_search/search_engines/base.py
freedom_search/search_engines/duckduckgo.py
freedom_search/search_engines/google.py
freedom_search-0.2.2.dist-info/LICENSE
freedom_search-0.2.2.dist-info/METADATA
freedom_search-0.2.2.dist-info/WHEEL
freedom_search-0.2.2.dist-info/top_level.txt
freedom_search-0.2.2.dist-info/RECORD
