Metadata-Version: 2.1
Name: freedom_search
Version: 0.2.2
Summary: Empower your AI models with ethical, open-source web intelligence
Home-page: https://github.com/ParisNeo/FreedomSearch
Author: ParisNeo
Author-email: parisneoai@gmail.com
Classifier: Development Status :: 3 - Alpha
Classifier: Intended Audience :: Developers
Classifier: License :: OSI Approved :: MIT License
Classifier: Operating System :: OS Independent
Classifier: Programming Language :: Python :: 3
Classifier: Programming Language :: Python :: 3.8
Classifier: Programming Language :: Python :: 3.9
Classifier: Programming Language :: Python :: 3.10
Classifier: Programming Language :: Python :: 3.11
Classifier: Programming Language :: Python :: 3.12
Requires-Python: >=3.8
License-File: LICENSE
Requires-Dist: bs4
Requires-Dist: requests ==2.32.3
Requires-Dist: setuptools ==70.2.0
Requires-Dist: ascii-colors >=0.4.0
Requires-Dist: pipmaster >=0.1.5
Requires-Dist: googlesearch-python
